{
    "repo": {
        "mipera": "CMIP6Plus",
        "repo": "actiontest_cmip6pluscvs",
        "url": "https://github.com/cmip-ipo-internal/actiontest_cmip6pluscvs",
        "version": "v6.5.6.1"
    },
    "changelog": {
        "last_changed": "2024/02/12 16:06 UTC",
        "comment": [
            "",
            "",
            "## Version Updated: v6.5.6.0 \u2192 v6.5.6.1",
            "",
            ">> `v\\{w\\}.\\{x\\}.\\{y\\}.\\{z\\}`",
            "For further information: [see the wiki](https://wiki.mipcvs.dev)",
            "",
            " ",
            "#### <ins>Version index \"z\" == 1</ins>",
            "- [x] **z** version number \u2191 :: *source_id (MIROC6)*",
            "- [x] **z** version number \u2191 :: *source_id (MPI-ESM1-2-LR)*",
            "- [x] **z** version number \u2191 :: *source_id (MPI-ESM1-2-HR)*"
        ]
    },
    "source_id": {
        "counts": 4,
        "keys": [
            "HadGEM3-GC31-LL",
            "MPI-ESM1-2-LR",
            "MPI-ESM1-2-HR",
            "MIROC6"
        ]
    },
    "experiment_id": {
        "counts": 28,
        "keys": [
            "1pctCO2",
            "abrupt-4xCO2",
            "amip",
            "esm-hist",
            "esm-piControl",
            "esm-piControl-spinup",
            "fut-Aer",
            "fut-GHG",
            "fut-lu",
            "fut-sol",
            "fut-totalO3",
            "fut-volc",
            "hist-GHG",
            "hist-aer",
            "hist-lu",
            "hist-nat",
            "hist-noLu",
            "hist-piGHG",
            "hist-piAer",
            "hist-piSol",
            "hist-piTotalO3",
            "hist-piVolc",
            "hist-sol",
            "hist-totalO3",
            "hist-volc",
            "historical",
            "piControl",
            "piControl-spinup"
        ]
    },
    "activity_id": {
        "counts": 2,
        "keys": [
            "CMIP",
            "LESFMIP"
        ]
    }
}